{
"skeleton": {
	"hash": "pEJJ1hexSfZw0OGFJ+cmfgJ+MiE",
	"spine": "3.8.75",
	"x": 356.56,
	"y": -322.17,
	"width": 200,
	"height": 200,
	"images": "./",
	"audio": ""
},
"bones": [
	{ "name": "root" },
	{ "name": "l2_bone", "parent": "root", "x": 0.0, "y": 0.0 }
],
"slots": [
	{ "name": "l2_slot", "bone": "l2_bone", "attachment": "l2" }
],
"skins": [
	{
		"name": "default",
		"attachments": {
			"l2_slot": {
				"l2": { "width": 200, "height": 200 }
			}
		}
	}
],
"animations": {
	"l2": {
		"bones": {
			"l2_bone": {
				"scale": [
					{},
					{ "time": 0.4333, "x": 1.15, "y": 1.15 },
					{ "time": 0.8333 }
				]
			}
		}
	}
}
}